trkjoy_mcp_demo/__init__.py
trkjoy_mcp_demo-0.1.3.dist-info/METADATA
trkjoy_mcp_demo-0.1.3.dist-info/WHEEL
trkjoy_mcp_demo-0.1.3.dist-info/entry_points.txt
trkjoy_mcp_demo-0.1.3.dist-info/RECORD
