Metadata-Version: 2.4
Name: trkjoy-mcp-demo
Version: 0.1.3
Summary: Add your description here
Author-email: kkblue <blue@qq.com>
Requires-Python: >=3.12.10
Requires-Dist: mcp[cli]>=1.11.0
Requires-Dist: requests
